even_dist/__init__.py
even_dist/even_dist.py
hello/__init__.py
hello/fadf.txt
hello/hello.txt
even_dist-0.3.2.dist-info/LICENSE
even_dist-0.3.2.dist-info/METADATA
even_dist-0.3.2.dist-info/WHEEL
even_dist-0.3.2.dist-info/top_level.txt
even_dist-0.3.2.dist-info/RECORD
