Metadata-Version: 2.1
Name: even-dist
Version: 0.3.2
Summary: My first Python library
Home-page: https://github.com/tic-top/even_dist/
Author: kirp
Author-email: kirp@umich.edu
License: MIT
Platform: UNKNOWN
License-File: LICENSE
Requires-Dist: numpy
Requires-Dist: matplotlib
